{
  "volumeSlug": "plautus-stichus-trinummus-truculentus-tale-of-a-travelling-bag-fragments-bj13xq",
  "volumeTitle": "Stichus. Trinummus. Truculentus. Tale of a Travelling Bag. Fragments",
  "authorDisplay": "Plautus",
  "authors": [
    "Plautus"
  ],
  "language": "latin",
  "status": "ready",
  "chunkSlug": "stichus-1vasmo-5",
  "label": "Stichus (Section 2.2.375 - Section 3.2.472)",
  "partId": "stichus-1vasmo",
  "partTitle": "Stichus",
  "originalLang": "la",
  "citations": {
    "original": {
      "label": "Scaife original text",
      "citation": "Stichus",
      "url": "https://scaife.perseus.org/library/urn:cts:latinLit:phi0119.phi018.perseus-lat2/"
    },
    "translation": {
      "label": "Scaife English translation",
      "citation": "Stichus, or The Parasite Rebuffed",
      "url": "https://scaife.perseus.org/library/urn:cts:latinLit:phi0119.phi018.perseus-eng2/"
    }
  },
  "sections": [
    {
      "id": "2.2.375",
      "label": "Section 2.2.375",
      "chapter": null,
      "original": "hercle vero capiam scopas atque hoc convorram lubens .",
      "translation": "I ’ faith , I ’ ll surely take the broom , and sweep this place with pleasure ."
    },
    {
      "id": "2.2.376",
      "label": "Section 2.2.376",
      "chapter": null,
      "original": "Lanam purpuramque multam .",
      "translation": "Wool and purple in plenty ."
    },
    {
      "id": "2.2.376b",
      "label": "Section 2.2.376b",
      "chapter": null,
      "original": "Em qui ventrem vestiam .",
      "translation": "Aye , for me to clothe my carcase with ."
    },
    {
      "id": "2.2.377",
      "label": "Section 2.2.377",
      "chapter": null,
      "original": "Lectos eburatos , auratos .",
      "translation": "Couches , adorned with ivory and gold ."
    },
    {
      "id": "2.2.377b",
      "label": "Section 2.2.377b",
      "chapter": null,
      "original": "Accubabo regie .",
      "translation": "I ’ ll recline at table right regally ."
    },
    {
      "id": "2.2.378",
      "label": "Section 2.2.378",
      "chapter": null,
      "original": "Tum Babylonica et peristroma tonsilia et tappetia",
      "translation": "Besides — Babylonian coverings for couches [*] , and carpets dyed in purple , has he brought ."
    },
    {
      "id": "2.2.379",
      "label": "Section 2.2.379",
      "chapter": null,
      "original": "advexit , nimium bonae rei .",
      "translation": "Abundance of fine things ."
    },
    {
      "id": "2.2.379b",
      "label": "Section 2.2.379b",
      "chapter": null,
      "original": "Hercle rem gestam bene .",
      "translation": "I ’ faith , his business has been successful ."
    },
    {
      "id": "2.2.380",
      "label": "Section 2.2.380",
      "chapter": null,
      "original": "Poste , ut occepi narrare , fidicinas , tibicinas ,",
      "translation": "Then , as I began to say , female players on the harp , on the pipe , sackbuts too [*] , has he brought with him , of surprising beauty ."
    },
    {
      "id": "2.2.381b",
      "label": "Section 2.2.381b",
      "chapter": null,
      "original": "Eugepae ,",
      "translation": "Capital ! When I ’ m at my wine , I ’ ll be quite sportive ; then am I in merriest pin ."
    },
    {
      "id": "2.2.383",
      "label": "Section 2.2.383",
      "chapter": null,
      "original": "Poste unguenta multigenerum multa .",
      "translation": "Besides many unguents of numerous kinds ."
    },
    {
      "id": "2.2.383b",
      "label": "Section 2.2.383b",
      "chapter": null,
      "original": "Non vendo logos .",
      "translation": "I ’ ll not sell my bon mots ; I ’ ll not have an auction now ; I ’ ve got an estate in fee [*] ."
    },
    {
      "id": "2.2.385",
      "label": "Section 2.2.385",
      "chapter": null,
      "original": "malivoli , perquisitores auctionum , perierint .",
      "translation": "Let the mischievous hunters of auctions go to perdition . Hercules , I congratulate thee that the tenths which I vowed to thee are increased . ’ Tis my hope that at length , by some means or other , I may expel this plaguy famine from my stomach ."
    },
    {
      "id": "2.2.388",
      "label": "Section 2.2.388",
      "chapter": null,
      "original": "Poste autem advexit parasitos secum .",
      "translation": "And then , besides , he has brought some Parasites [*] with him ."
    },
    {
      "id": "2.2.388b",
      "label": "Section 2.2.388b",
      "chapter": null,
      "original": "Ei , perii miser .",
      "translation": "Alas ! to my confusion , I ’ m undone ."
    },
    {
      "id": "2.2.389",
      "label": "Section 2.2.389",
      "chapter": null,
      "original": "Ridiculissumos .",
      "translation": "Right funny fellows ."
    },
    {
      "id": "2.2.389b",
      "label": "Section 2.2.389b",
      "chapter": null,
      "original": "Revorram hercle hoc quod converri modo .",
      "translation": "I ’ faith , I ’ ll sweep this dust back , which I just now swept together . ( Sweeps it back .)"
    },
    {
      "id": "2.2.390",
      "label": "Section 2.2.390",
      "chapter": null,
      "original": "Vidistin virum sororis Pamphilum ?",
      "translation": "Did you see Pamphilus , the husband of my sister ?"
    },
    {
      "id": "2.2.390b",
      "label": "Section 2.2.390b",
      "chapter": null,
      "original": "Non .",
      "translation": "No ."
    },
    {
      "id": "2.2.390c",
      "label": "Section 2.2.390c",
      "chapter": null,
      "original": "Non adest ?",
      "translation": "Isn ’ t he there ?"
    },
    {
      "id": "2.2.391",
      "label": "Section 2.2.391",
      "chapter": null,
      "original": "Immo venisse eum simitu aiebat ille : ego huc citus",
      "translation": "Yes , they said that he had come as well . I ran hither before them , with all speed , that I might bring the welcome tidings ."
    },
    {
      "id": "2.2.393",
      "label": "Section 2.2.393",
      "chapter": null,
      "original": "Venales logi sunt illi , quos negabam vendere .",
      "translation": "Those bon mots are now on sale , which I was saying I wouldn ’ t sell . I ’ m done for : now there is occasion for spiteful persons to rejoice at my misfortune ."
    },
    {
      "id": "2.2.395",
      "label": "Section 2.2.395",
      "chapter": null,
      "original": "Hercules , qui deus sis , sane discessisti non bene .",
      "translation": "Hercules , thou who art a God , thou really hast departed not opportunely ."
    },
    {
      "id": "2.2.396",
      "label": "Section 2.2.396",
      "chapter": null,
      "original": "I intro , Pinacium , iube fámulos rem divinam mi apparent .",
      "translation": "Go in-doors , Pinacium ; bid the servants prepare the sacred things [*] for me . ( To GELASIMUS .) Fare you well !"
    },
    {
      "id": "2.2.397b",
      "label": "Section 2.2.397b",
      "chapter": null,
      "original": "Vin administrem ?",
      "translation": "Do you want me to assist ?"
    },
    {
      "id": "2.2.397c",
      "label": "Section 2.2.397c",
      "chapter": null,
      "original": "Sat servorum habeo domi .—",
      "translation": "I have servants enough in the house ."
    },
    {
      "id": "2.2.398",
      "label": "Section 2.2.398",
      "chapter": null,
      "original": "Enim vero , Gelasime , opinor provenisti futtile ,",
      "translation": "In good sooth , Gelasimus , I doubt you have come to but little purpose , if neither he that is here gives you any aid , nor yet he that ’ s coming ."
    },
    {
      "id": "2.2.400",
      "label": "Section 2.2.400",
      "chapter": null,
      "original": "ibo intro ad libros et discam de dictis melioribus ;",
      "translation": "I ’ ll off indoors to my books [*] , and take my instructions from the cleverest sayings ; for if I don ’ t drive away those fellows , the Parasites that are coming , most surely I ’ m undone ."
    },
    {
      "id": "3.1.402",
      "label": "Section 3.1.402",
      "chapter": null,
      "original": "Quom bene re gesta salvos convortor domum ,",
      "translation": "Inasmuch as , my business prosperously carried on , I am returned safe home , thanks do I return to Neptune and to his tempests ; to Mercury as well [*] , who in my traffic"
    },
    {
      "id": "3.1.405",
      "label": "Section 3.1.405",
      "chapter": null,
      "original": "iuvit lucrisque quadruplicavit rem meam .",
      "translation": "has aided me , and by my profits has rendered my property fourfold . Those whom formerly I affected with sorrow at my departure , the same shall I now make joyous at my arrival . But already have I met my connexion Antipho , and from bad terms have I returned to friendship with him ."
    },
    {
      "id": "3.1.410",
      "label": "Section 3.1.410",
      "chapter": null,
      "original": "videte , quaeso , quid potest pecunia :",
      "translation": "See , prithee , what money can effect . Since , my affairs prospering , he sees that I ’ ve returned , and brought home great wealth , without any mediators , there on board the ship , upon the deck , we have returned to friendship and good feeling ."
    },
    {
      "id": "3.1.415",
      "label": "Section 3.1.415",
      "chapter": null,
      "original": "et is hodie apud me cenat et frater meus ;",
      "translation": "Both he and my brother dine with me this day ; for yesterday we were both in the same harbour [*] together ; but to-day my ship weighed anchor a little the soonest . Take these people in-doors , Stichus , whom [*] I ’ ve brought with me ."
    },
    {
      "id": "3.1.419",
      "label": "Section 3.1.419",
      "chapter": null,
      "original": "Ere , sí ego taceam seu loquar , scio scire te",
      "translation": "Master , whether I ’ m silent or speak , I ’ m sure you know"
    },
    {
      "id": "3.1.420",
      "label": "Section 3.1.420",
      "chapter": null,
      "original": "quam multas tecum miserias mulcaverim .",
      "translation": "how many hardships I ’ ve endured in your service ; now , on my arrival home , I wish to spend in freedom [*] this one day after these many hardships ."
    },
    {
      "id": "3.1.423",
      "label": "Section 3.1.423",
      "chapter": null,
      "original": "Et ius et aequom postulas : sumas , Stiche .",
      "translation": "You ask what ’ s just and right . Stlchus , you may take this day for yourself ; I don ’ t object to it . Go where you like ."
    },
    {
      "id": "3.1.425",
      "label": "Section 3.1.425",
      "chapter": null,
      "original": "cadum tibi veteris vini propino .",
      "translation": "A cask , too , of old wine , I give you to drink ."
    },
    {
      "id": "3.1.425b",
      "label": "Section 3.1.425b",
      "chapter": null,
      "original": "Papae ,",
      "translation": "O , grand ! I ’ ll have my mistress this day ."
    },
    {
      "id": "3.1.426b",
      "label": "Section 3.1.426b",
      "chapter": null,
      "original": "Vel decem , dum de tuo .",
      "translation": "Even ten , so long as it is at your own expense ."
    },
    {
      "id": "3.1.427",
      "label": "Section 3.1.427",
      "chapter": null,
      "original": "Quid ? hoc etiam unum ?",
      "translation": "What ⋯ ?"
    },
    {
      "id": "3.1.427b",
      "label": "Section 3.1.427b",
      "chapter": null,
      "original": "Quid id autem unumst ? expedi .",
      "translation": "What ⋯ ?"
    },
    {
      "id": "3.1.428",
      "label": "Section 3.1.428",
      "chapter": null,
      "original": "Ad cenam ibone ?",
      "translation": "I ’ ll go and dine ⋯"
    },
    {
      "id": "3.1.429",
      "label": "Section 3.1.429",
      "chapter": null,
      "original": "Sic hoc placet ; rogatu necne , nil moror .",
      "translation": "’ Tis thus it pleases me ⋯"
    },
    {
      "id": "3.1.430",
      "label": "Section 3.1.430",
      "chapter": null,
      "original": "Vbi cenas hodie ?",
      "translation": "Where do you dine to-day ?"
    },
    {
      "id": "3.1.430b",
      "label": "Section 3.1.430b",
      "chapter": null,
      "original": "Sic hanc rationem institi :",
      "translation": "This plan have I thus resolved upon . I have a mistress here in the neighbourhood , Stephanium , the servantmaid of your brother . I ’ m going to invite her ; I ’ ll take her to a pic-nic entertainment [*] at her fellow-servant ’ s , Sagarinus We both have the same mistress ; we are rivals ."
    },
    {
      "id": "3.1.435",
      "label": "Section 3.1.435",
      "chapter": null,
      "original": "Age abduce hasce intro . hunc tibi dedo diem .",
      "translation": "Come then , conduct them in . I grant you this day ."
    },
    {
      "id": "3.1.436",
      "label": "Section 3.1.436",
      "chapter": null,
      "original": "Meam culpam habeto , nisi probe excruciavero .",
      "translation": "Hold me to blame if I don ’ t make the most of it [*] . Troth now , I ’ ll pass through the garden to my mistress , to engage her beforehand for me this evening ; at the same time I ’ ll give my contribution , and bid the dinner to be cooked at Sagarinus ’ s ,"
    },
    {
      "id": "3.1.440",
      "label": "Section 3.1.440",
      "chapter": null,
      "original": "aut egomet ibo atque opsonabo opsonium .",
      "translation": "or else I ’ ll go myself and make my marketing as caterer . Sagarinus , ⋯ ⋯ a servant ⋯ for my ⋯ with stripes ⋯ to take him home well thrashed ,"
    },
    {
      "id": "3.1.445",
      "label": "Section 3.1.445",
      "chapter": null,
      "original": "parata res faciam ut sit . egomet me moror .",
      "translation": "I ’ ll make all things to be in readiness here ; but I ’ m delaying myself . And don ’ t you be surprised [*] ( to the AUDIENCE ) that men , who are slaves , drink , court , and give invitations to dinner ? This is allowed us at Athens . But when I think of it , rather than meet with censure , there ’ s here , too ,"
    },
    {
      "id": "3.1.450",
      "label": "Section 3.1.450",
      "chapter": null,
      "original": "aliud posticum nostrarum harunc aedium :",
      "translation": "another door to the back buildings of our house . I ’ ll go that way to market ; by that way I ’ ll bring back the provisions — through the garden there ’ s a passage that communicates with both houses . ( To the SLAVES .) Do you follow me this way . I surely will pull this day to bits [*] ."
    },
    {
      "id": "3.2.454",
      "label": "Section 3.2.454",
      "chapter": null,
      "original": "Libros inspexi ; tam confido quam potis ,",
      "translation": "I ’ ve consulted my books ; I ’ m as sure as possible ,"
    },
    {
      "id": "3.2.455",
      "label": "Section 3.2.455",
      "chapter": null,
      "original": "me meum optenturum regem ridiculis meis .",
      "translation": "that by my funny bon mots I shall recover my patron [*] . Now I ’ m going to see whether he has arrived by this from the harbour , that when he comes I may smooth him down with my speeches ."
    },
    {
      "id": "3.2.458",
      "label": "Section 3.2.458",
      "chapter": null,
      "original": "Hic quidém Gelasimus est parasitus , qui venit .",
      "translation": "Surely , this is Gelasimus , the Parasite , that ’ s coming ."
    },
    {
      "id": "3.2.459",
      "label": "Section 3.2.459",
      "chapter": null,
      "original": "Auspicio hodie óptumo exivi foras :",
      "translation": "With lucky auspices , by my troth , this day did I come out of doors ;"
    },
    {
      "id": "3.2.460",
      "label": "Section 3.2.460",
      "chapter": null,
      "original": "mustela murem ábstulit praeter pedes ;",
      "translation": "since an omen auspiciously befel me [*] . This was beheld by me ; how a weasel carried off a mouse close at my feet . For as she found sustenance for herself this day , so do I hope that I shall do , as the augury predicts ."
    },
    {
      "id": "3.2.465",
      "label": "Section 3.2.465",
      "chapter": null,
      "original": "o Épignome , ut ego nunc te conspicio libens ,",
      "translation": "( Sees EPIGNOMUS .) Surely this is Epignomus that ’ s standing here ; I ’ ll go and address him . My dear Epignomus , how pleased I am to see you now ; how my tears are starting forth for very joy . Have you all along enjoyed your health ?"
    },
    {
      "id": "3.2.467b",
      "label": "Section 3.2.467b",
      "chapter": null,
      "original": "Sustentatumst sedulo .",
      "translation": "With care it has been preserved ."
    },
    {
      "id": "3.2.468",
      "label": "Section 3.2.468",
      "chapter": null,
      "original": "Propino tibi salutem plenis faucibus .",
      "translation": "Right heartily I wish you health [*] ."
    },
    {
      "id": "3.2.469",
      "label": "Section 3.2.469",
      "chapter": null,
      "original": "Bene atque amice dicis . di dent quae velis .",
      "translation": "You speak kindly , and like a friend . May the Gods grant what you wish ."
    },
    {
      "id": "3.2.470_471",
      "label": "Section 3.2.470_471",
      "chapter": null,
      "original": "Cenem illi apud te , quoniam salvos advenis .",
      "translation": "I , sup there with you ?"
    },
    {
      "id": "3.2.472",
      "label": "Section 3.2.472",
      "chapter": null,
      "original": "Locatast opera nunc quidem ; tam gratiast .",
      "translation": "Really , an engagement has been made already ; but I give you thanks ."
    }
  ],
  "prevChunkSlug": "stichus-1vasmo-4",
  "nextChunkSlug": "stichus-1vasmo-6"
}
