{
  "volumeSlug": "plautus-amphitryon-the-comedy-of-asses-the-pot-of-gold-the-two-bacchises-the-captives-najy9a",
  "volumeTitle": "Amphitryon. The Comedy of Asses. The Pot of Gold. The Two Bacchises. The Captives",
  "authorDisplay": "Plautus",
  "authors": [
    "Plautus"
  ],
  "language": "latin",
  "status": "ready",
  "chunkSlug": "the-pot-of-gold-12wtur-4",
  "label": "The Pot of Gold (Section 2.4.307 - Section 2.8.380)",
  "partId": "the-pot-of-gold-12wtur",
  "partTitle": "The Pot of Gold",
  "originalLang": "la",
  "citations": {
    "original": {
      "label": "Scaife original text",
      "citation": "Aulularia",
      "url": "https://scaife.perseus.org/library/urn:cts:latinLit:phi0119.phi003.perseus-lat2/"
    },
    "translation": {
      "label": "Scaife English translation",
      "citation": "Aulularia, or The Concealed Treasure",
      "url": "https://scaife.perseus.org/library/urn:cts:latinLit:phi0119.phi003.perseus-eng2/"
    }
  },
  "sections": [
    {
      "id": "2.4.307",
      "label": "Section 2.4.307",
      "chapter": null,
      "original": "Immo equidem credo .",
      "translation": "Why really , I do believe you ."
    },
    {
      "id": "2.4.307b",
      "label": "Section 2.4.307b",
      "chapter": null,
      "original": "At scin etiam quo modo ?",
      "translation": "But , further , do you know how it is ?"
    },
    {
      "id": "2.4.308",
      "label": "Section 2.4.308",
      "chapter": null,
      "original": "aquam hercle plorat , cum lavat , profundere .",
      "translation": "I ’ faith , he grieves to throw away the water when he washes ."
    },
    {
      "id": "2.4.309",
      "label": "Section 2.4.309",
      "chapter": null,
      "original": "Censen talentum magnum exorari pote",
      "translation": "Do you think a great talent [*]"
    },
    {
      "id": "2.4.310",
      "label": "Section 2.4.310",
      "chapter": null,
      "original": "ab istóc sene ut det , qui fiamus liberi ?",
      "translation": "might be begged of this old fellow for him to give us , through which we might become free ?"
    },
    {
      "id": "2.4.311",
      "label": "Section 2.4.311",
      "chapter": null,
      "original": "Famem hercle utendam si roges , numquam dabit .",
      "translation": "By my troth , if you were to ask it , he would never let you have the loan of hunger . Why , the other day , the barber had cut his nails [*] ; he collected all the parings , and carried them off ."
    },
    {
      "id": "2.4.314",
      "label": "Section 2.4.314",
      "chapter": null,
      "original": "Edepol mortalem parce parcum praedicas .",
      "translation": "I ’ faith , you do describe a miserably stingy wretch ."
    },
    {
      "id": "2.4.315",
      "label": "Section 2.4.315",
      "chapter": null,
      "original": "Censen vero esse parcum et misere vivere ?",
      "translation": "But do you think that he does live so very stingily and wretchedly ?"
    },
    {
      "id": "2.4.316",
      "label": "Section 2.4.316",
      "chapter": null,
      "original": "pulmentum pridem éi eripuit miluos :",
      "translation": "A kite , the other day , carried off his morsel of food ; the fellow went crying to the Praetor [*] ; there , weeping and lamenting , he began to request that he might be allowed to compel the kite to give bail ."
    },
    {
      "id": "2.4.320",
      "label": "Section 2.4.320",
      "chapter": null,
      "original": "sescenta sunt quae memorem , si sit otium .",
      "translation": "There are innumerable other things that I could mention , if I had the leisure . But which of you two is the sharper ? Tell me ."
    },
    {
      "id": "2.4.322",
      "label": "Section 2.4.322",
      "chapter": null,
      "original": "Ego , et multo melior .",
      "translation": "I — as being much the better one ."
    },
    {
      "id": "2.4.322b",
      "label": "Section 2.4.322b",
      "chapter": null,
      "original": "Cocum ego , non furem rogo .",
      "translation": "A cook I ask for , not a thief [*] ."
    },
    {
      "id": "2.4.323",
      "label": "Section 2.4.323",
      "chapter": null,
      "original": "Cocum ergo dico .",
      "translation": "As a cook , I mean ."
    },
    {
      "id": "2.4.323b",
      "label": "Section 2.4.323b",
      "chapter": null,
      "original": "Quid tu ais ?",
      "translation": "What do you say ?"
    },
    {
      "id": "2.4.323c",
      "label": "Section 2.4.323c",
      "chapter": null,
      "original": "Sic sum ut vides .",
      "translation": "I ’ m just as you see me ."
    },
    {
      "id": "2.4.324",
      "label": "Section 2.4.324",
      "chapter": null,
      "original": "Cocus ille nundinalest , in nonum diem",
      "translation": "He ’ s a nine-day cook [*] ; every ninth day"
    },
    {
      "id": "2.4.325",
      "label": "Section 2.4.325",
      "chapter": null,
      "original": "solet ire coctum .",
      "translation": "he ’ s in the habit of going out to cook ."
    },
    {
      "id": "2.4.325b",
      "label": "Section 2.4.325b",
      "chapter": null,
      "original": "Tun , trium litterarum homo ,",
      "translation": "You , you three-lettered fellow [*] ;"
    },
    {
      "id": "2.4.326",
      "label": "Section 2.4.326",
      "chapter": null,
      "original": "me vituperas ? fur .",
      "translation": "do you abuse me , you thief ?"
    },
    {
      "id": "2.4.326b",
      "label": "Section 2.4.326b",
      "chapter": null,
      "original": "Etiam fur , trifurcifer .",
      "translation": "To be sure I do , you trebly-distilled thief of thieves [*] ."
    },
    {
      "id": "2.5.327",
      "label": "Section 2.5.327",
      "chapter": null,
      "original": "Tace nunciam tu , atque agnum hinc uter est pinguior",
      "translation": "Now do you hold your tongue for the present , and , that lamb , whichever is the fatter of the two —"
    },
    {
      "id": "2.5.328b",
      "label": "Section 2.5.328b",
      "chapter": null,
      "original": "Licet .—",
      "translation": "Very well [*] ."
    },
    {
      "id": "2.5.328c",
      "label": "Section 2.5.328c",
      "chapter": null,
      "original": "Tu , Congrio ,",
      "translation": "Do you , Congrio ,"
    },
    {
      "id": "2.5.328a",
      "label": "Section 2.5.328a",
      "chapter": null,
      "original": "quem illic reliquit agnum , eum sume atque abi",
      "translation": "take that , and go in-doors there ( pointing to EUCLIO ’ S house ; and ( to a MUSIC-GIRL and some of the PEOPLE with provisions ) do you follow him ;"
    },
    {
      "id": "2.5.330",
      "label": "Section 2.5.330",
      "chapter": null,
      "original": "vos ceteri ite huc ad nos .",
      "translation": "the rest of you this way , to our house ."
    },
    {
      "id": "2.5.330b",
      "label": "Section 2.5.330b",
      "chapter": null,
      "original": "Hercle iniuria",
      "translation": "By my troth , you ’ ve made an unfair"
    },
    {
      "id": "2.5.331",
      "label": "Section 2.5.331",
      "chapter": null,
      "original": "dispertivisti : pinguiorem agnum isti habent .",
      "translation": "division ; they ’ ve got the fattest lamb ."
    },
    {
      "id": "2.5.332",
      "label": "Section 2.5.332",
      "chapter": null,
      "original": "At nunc tibi dabitur pinguior tibicina .",
      "translation": "But the fattest music-girl shall be given you then . Do you , therefore , go along with him , Phrygia [*] . And do you , Eleusium , step in-doors here , to our house ."
    },
    {
      "id": "2.5.334b",
      "label": "Section 2.5.334b",
      "chapter": null,
      "original": "O Pythodice subdole ,",
      "translation": "O you crafty Strobilus ,"
    },
    {
      "id": "2.5.335",
      "label": "Section 2.5.335",
      "chapter": null,
      "original": "hucine detrusti me ad senem parcissimum ?",
      "translation": "have you pushed me off here upon this most miserly old fellow , where if I ask for anything , I may ask even to hoarseness before anything ’ s found me ?"
    },
    {
      "id": "2.5.337b",
      "label": "Section 2.5.337b",
      "chapter": null,
      "original": "Stultus et sine gratia es .",
      "translation": "’ Tis very foolish , and ’ tis thanklessly done , to do a service to you , when what you do goes for nothing ."
    },
    {
      "id": "2.5.339",
      "label": "Section 2.5.339",
      "chapter": null,
      "original": "Qui vero ?",
      "translation": "But how so ?"
    },
    {
      "id": "2.5.339b",
      "label": "Section 2.5.339b",
      "chapter": null,
      "original": "Rogitas ? iam principio in aedibus",
      "translation": "Do you ask ? In the first place then , there will be no confusion for you there in the house ; if you want anything to use ,"
    },
    {
      "id": "2.5.341",
      "label": "Section 2.5.341",
      "chapter": null,
      "original": "domo abs te adferto , ne operam perdas poscere .",
      "translation": "bring it from your own home , don ’ t lose your trouble in asking for it . But here , at our house , there ’ s great confusion , and a large establishment — furniture , gold , garments , silver vessels . If anything ’ s lost here ( as I know"
    },
    {
      "id": "2.5.345",
      "label": "Section 2.5.345",
      "chapter": null,
      "original": "facile abstinere posse , si nihil obviam est ),",
      "translation": "that you can easily [*] keep hands off — if nothing ’ s in your way ), they may say , The cooks have stolen it ; seize them , bind them , beat them , thrust them in the dungeon [*] . Nothing of that sort will happen to you , inasmuch as there will be nothing for you to steal . Follow me this way ."
    },
    {
      "id": "2.5.349b",
      "label": "Section 2.5.349b",
      "chapter": null,
      "original": "Sequor .",
      "translation": "I follow ."
    },
    {
      "id": "2.6.350",
      "label": "Section 2.6.350",
      "chapter": null,
      "original": "Heus , Staphyla , prodi atque ostium aperi .",
      "translation": "Ho , there Staphyla , come out and open the door ."
    },
    {
      "id": "2.6.350b",
      "label": "Section 2.6.350b",
      "chapter": null,
      "original": "Qui vocat ?",
      "translation": "Who calls there ?"
    },
    {
      "id": "2.6.351",
      "label": "Section 2.6.351",
      "chapter": null,
      "original": "Pythodicus .",
      "translation": "Strobilus ."
    },
    {
      "id": "2.6.351b",
      "label": "Section 2.6.351b",
      "chapter": null,
      "original": "Quid vis ?",
      "translation": "What do you want ?"
    },
    {
      "id": "2.6.351c",
      "label": "Section 2.6.351c",
      "chapter": null,
      "original": "Hos ut accipias coquos",
      "translation": "For you to take in these cooks , and this music-girl , and these provisions for the wedding . Megadorus bade me take these things to Euclio ."
    },
    {
      "id": "2.6.354",
      "label": "Section 2.6.354",
      "chapter": null,
      "original": "Cererin , Pythodice , has sunt facturi nuptias ?",
      "translation": "Are you about to make this wedding , Strobilus , in honor of Ceres [*] ?"
    },
    {
      "id": "2.6.355",
      "label": "Section 2.6.355",
      "chapter": null,
      "original": "Qui ?",
      "translation": "Why ?"
    },
    {
      "id": "2.6.355b",
      "label": "Section 2.6.355b",
      "chapter": null,
      "original": "Quia temeti nihil allatum intellego .",
      "translation": "Because I don ’ t see any wine brought ."
    },
    {
      "id": "2.6.356",
      "label": "Section 2.6.356",
      "chapter": null,
      "original": "At iam afferetur , si a foro ipsus redierit .",
      "translation": "Why , that will be brought just now , when he himself comes back from the market ."
    },
    {
      "id": "2.6.357",
      "label": "Section 2.6.357",
      "chapter": null,
      "original": "Ligna hic apud nos nulla sunt .",
      "translation": "There ’ s no firewood here in our house ."
    },
    {
      "id": "2.6.357b",
      "label": "Section 2.6.357b",
      "chapter": null,
      "original": "Sunt asseres ?",
      "translation": "There are the beams ."
    },
    {
      "id": "2.6.358",
      "label": "Section 2.6.358",
      "chapter": null,
      "original": "Sunt pol .",
      "translation": "I ’ faith , there are ."
    },
    {
      "id": "2.6.358b",
      "label": "Section 2.6.358b",
      "chapter": null,
      "original": "Sunt igitur ligna , ne quaeras foris .",
      "translation": "There is wood , then ; don ’ t you be seeking it out of doors ."
    },
    {
      "id": "2.6.359",
      "label": "Section 2.6.359",
      "chapter": null,
      "original": "Quid , impurate ? quamquam Volcano studes ,",
      "translation": "What , you unpurified fellow [*] , although your business is with the fire ,"
    },
    {
      "id": "2.6.360",
      "label": "Section 2.6.360",
      "chapter": null,
      "original": "cenaene causa aut tuae mercedis gratia",
      "translation": "for the sake of a dinner , or of your own hire , do you request us to set our house on fire ?"
    },
    {
      "id": "2.6.362",
      "label": "Section 2.6.362",
      "chapter": null,
      "original": "Haud postulo .",
      "translation": "I don ’ t ask you ."
    },
    {
      "id": "2.6.362b",
      "label": "Section 2.6.362b",
      "chapter": null,
      "original": "Duc istos intro .",
      "translation": "Take them in-doors ."
    },
    {
      "id": "2.6.362c",
      "label": "Section 2.6.362c",
      "chapter": null,
      "original": "Sequimini .—",
      "translation": "Follow me ."
    },
    {
      "id": "2.7.363",
      "label": "Section 2.7.363",
      "chapter": null,
      "original": "Curate . ego intervisam quid faciant coqui ;",
      "translation": "Mind you your business ; I ’ ll step in and see what the cooks are doing , to observe whom , i ’ faith , to-day it is a most laborious task ."
    },
    {
      "id": "2.7.365",
      "label": "Section 2.7.365",
      "chapter": null,
      "original": "nisi unum hoc faciam , ut in puteo cenam coquant :",
      "translation": "Unless I manage this one thing , for them to cook the dinner down in the dungeon [*] ; thence , when cooked , we might bring it up again in small baskets . But if they should eat below [*] whatever they should cook , those above would go without their dinner , and those below have dined . But here am I chattering , as though I had no business ,"
    },
    {
      "id": "2.7.370",
      "label": "Section 2.7.370",
      "chapter": null,
      "original": "rapacidarum ubi tantum sit in aedibus .",
      "translation": "when there ’ s such a pack of thieves in the house ."
    },
    {
      "id": "2.8.371",
      "label": "Section 2.8.371",
      "chapter": null,
      "original": "Volui animum tandem confirmare hodie meum ,",
      "translation": "I wished at length to screw up my courage to-day , so as to enjoy myself at the wedding of my daughter . I come to the market , I enquire about fish ; they tell me that it is dear , that lamb is dear , beef is dear ,"
    },
    {
      "id": "2.8.375",
      "label": "Section 2.8.375",
      "chapter": null,
      "original": "vitulinam , cetum , porcinam : cara omnia .",
      "translation": "veal , large fish [*] , and pork , all of them are dear . And for this reason were they still dearer ; I hadn ’ t the money . I came away thence in a rage , since I had nothing wherewithal to make a purchase ; and thus did I baulk [*] all those rascals . Then I began to think with myself upon the road ,"
    },
    {
      "id": "2.8.380",
      "label": "Section 2.8.380",
      "chapter": null,
      "original": "occepi : festo die si quid prodegeris ,",
      "translation": "If you are guilty of any extravagance on a festive day , you may be wanting on a common day , unless you are saving . After I disclosed this reasoning to my heart and appetite , my mind came over to my opinion , that I ought to give my daughter in marriage at as little expense as possible ."
    }
  ],
  "prevChunkSlug": "the-pot-of-gold-12wtur-3",
  "nextChunkSlug": "the-pot-of-gold-12wtur-5"
}
